README.rst
setup.py
HippodamiaAgent.egg-info/PKG-INFO
HippodamiaAgent.egg-info/SOURCES.txt
HippodamiaAgent.egg-info/dependency_links.txt
HippodamiaAgent.egg-info/requires.txt
HippodamiaAgent.egg-info/top_level.txt
hippodamia_agent/__init__.py
hippodamia_agent/get_schema.py
hippodamia_agent/monitoringagent.py
hippodamia_agent/mqtthandler.py
hippodamia_agent/states/__init__.py
hippodamia_agent/states/aagentstate.py
hippodamia_agent/states/active.py
hippodamia_agent/states/event_ids.py
hippodamia_agent/states/history_type.py
hippodamia_agent/states/initialized.py
hippodamia_agent/states/machinelogger.py
hippodamia_agent/states/onboarded.py
hippodamia_agent/states/onboarding.py
hippodamia_agent/states/state_ids.py
hippodamia_agent/states/state_machine.py
hippodamia_agent/states/terminiating.py
hippodamia_agent/states/uninitialized.py
tests_unit/__init__.py
tests_unit/test_validateconfig.py